{"nodes": [{"id": "app_minimal_resume_layout_js", "label": "layout.js", "file_type": "code", "source_file": "app\\(minimal-resume)\\layout.js", "source_location": "L1"}, {"id": "layout_resumelayout", "label": "ResumeLayout()", "file_type": "code", "source_file": "app\\(minimal-resume)\\layout.js", "source_location": "L9"}], "edges": [{"source": "app_minimal_resume_layout_js", "target": "globals_css", "relation": "imports_from", "confidence": "EXTRACTED", "source_file": "app\\(minimal-resume)\\layout.js", "source_location": "L1", "weight": 1.0}, {"source": "app_minimal_resume_layout_js", "target": "all_css", "relation": "imports_from", "confidence": "EXTRACTED", "source_file": "app\\(minimal-resume)\\layout.js", "source_location": "L2", "weight": 1.0}, {"source": "app_minimal_resume_layout_js", "target": "layout_resumelayout", "relation": "contains", "confidence": "EXTRACTED", "source_file": "app\\(minimal-resume)\\layout.js", "source_location": "L9", "weight": 1.0}], "raw_calls": []}